<transpose latex_name="\transpose" lhs="matrix" title="T" type="phrasegroup">
  <mes>
    <me name="entity" />
    <me name="phrase" />
    <me name="phrasegroup" />
    <me name="transpose" />
  </mes>
  <characteristics>
    <ch name="_bodmasable" />
  </characteristics>
  <inherited_properties>
    <ip name="font_size" type="int" value="45" />
    <ip name="bold" type="bool" value="False" />
    <ip name="font_size_coeff" type="float" value="1.0" />
    <ip name="rgb_colour" type="tuple">
      <ti type="float" value="0.0" />
      <ti type="float" value="0.0" />
      <ti type="float" value="0.0" />
    </ip>
    <ip name="font_size_combined_coeff" type="float" value="1.0" />
  </inherited_properties>
  <properties>
    <property name="phraser" type="str" value="expression" />
    <property name="highlight_group" type="bool" value="True" />
    <property name="name" type="str" value="phrase_76769544" />
    <property name="enterable" type="bool" value="False" />
    <property name="wordlike" type="bool" value="True" />
  </properties>
  <entities>
    <phrase_86126032 available="False,False,True,False" type="script">
      <targets>
        <target name="site2" type="target_phrase">
          <properties>
            <property name="enterable" type="bool" value="False" />
            <property name="attachable" type="bool" value="False" />
            <property name="name" type="str" value="site2" />
            <property name="deletable" type="int" value="2" />
          </properties>
          <entities>
            <entity_82646728 ink="False" shape="T" type="symbol">
              <properties>
                <property name="name" type="str" value="entity_82646728" />
                <property name="attachable" type="bool" value="False" />
              </properties>
            </entity_82646728>
          </entities>
        </target>
        <target name="expression" type="target_phrase">
          <properties>
            <property name="enterable" type="bool" value="False" />
            <property name="name" type="str" value="expression" />
            <property name="deletable" type="int" value="2" />
          </properties>
          <entities>
            <phrase_86126104 target="matrix" type="phrase">
              <properties>
                <property name="name" type="str" value="phrase_86126104" />
                <property name="attachable" type="bool" value="False" />
              </properties>
            </phrase_86126104>
          </entities>
        </target>
      </targets>
    </phrase_86126032>
  </entities>
  <targets>
    <target name="matrix" type="target_phrase">
      <properties>
        <property name="name" type="str" value="matrix" />
        <property name="deletable" type="int" value="2" />
      </properties>
    </target>
  </targets>
  <latex>"{%s}^{T}" % self["matrix"].to_latex()</latex>
  <sympy>self["matrix"].get_sympy().transpose()</sympy>
  <string>u'%s^T' % self["matrix"].to_string()</string>
  <symbol>T</symbol>
  <category>Matrices</category>
  <shortcut>&lt;Shift&gt;&lt;Alt&gt;t</shortcut>
</transpose>
