<?xml version="1.0"?>
<object name="portal_properties" meta_type="Plone Properties Tool">
  <object name="zipfile_properties" meta_type="Plone Property Sheet">
    <property name="title">Zip File Tool</property>
    <property name="image_type" type="string">Image</property>
    <property name="file_type" type="string">File</property>
    <property name="doc_type" type="string">Document</property>
    <property name="folder_type" type="string">Folder</property>
    <property name="content_mappings" type="lines">
      <element value="ATFile:zipfile_atfile"/>
      <element value="ATImage:zipfile_atimage"/>
      <element value="ATDocument:zipfile_atdocument"/>
      <element value="ATLink:zipfile_atlink"/>
      <element value="ATEvent:zipfile_atevent"/>
      <element value="ATFavorite:zipfile_atfavorite"/>
      <element value="ATNewsItem:zipfile_atnewsitem"/>
      <element value="ATFolder:zipfile_atfolder"/>
    </property>
  </object>
</object>
